[
  {
    "date": "2009-01",
    "rate": 3.1
  },
  {
    "date": "2009-02",
    "rate": 3.0
  },
  {
    "date": "2009-03",
    "rate": 2.9
  },
  {
    "date": "2009-04",
    "rate": 3.4
  },
  {
    "date": "2009-05",
    "rate": 3.8
  },
  {
    "date": "2009-06",
    "rate": 3.7
  },
  {
    "date": "2009-07",
    "rate": 5.1
  },
  {
    "date": "2009-08",
    "rate": 5.0
  },
  {
    "date": "2009-09",
    "rate": 4.9
  },
  {
    "date": "2009-10",
    "rate": 4.7
  },
  {
    "date": "2009-11",
    "rate": 5.2
  },
  {
    "date": "2009-12",
    "rate": 5.6
  }
]
